ormtastic/.DS_Store
ormtastic/__about__.py
ormtastic/__init__.py
ormtastic-0.0.1.dist-info/METADATA
ormtastic-0.0.1.dist-info/WHEEL
ormtastic-0.0.1.dist-info/licenses/LICENSE
ormtastic-0.0.1.dist-info/RECORD
